cyclic_sequences/__init__.py
cyclic_sequences/cyclic_sequences.py
cyclic_sequences-1.1.2.dist-info/DESCRIPTION.rst
cyclic_sequences-1.1.2.dist-info/METADATA
cyclic_sequences-1.1.2.dist-info/RECORD
cyclic_sequences-1.1.2.dist-info/WHEEL
cyclic_sequences-1.1.2.dist-info/metadata.json
cyclic_sequences-1.1.2.dist-info/top_level.txt
