Metadata-Version: 2.0
Name: cyclic-sequences
Version: 1.1.2
Summary: A collection of cyclic sequence objects.
Home-page: https://github.com/bclmary/cyclic_sequences.git
Maintainer: BCL Mary
Maintainer-email: bclmary@mailoo.org
License: GPL-3.0+
Keywords: cyclic sequence tuple list
Platform: any
Classifier: Development Status :: 5 - Production/Stable
Classifier: License :: OSI Approved :: GNU General Public License v3 or later (GPLv3+)
Classifier: Natural Language :: English
Classifier: Environment :: Console
Classifier: Programming Language :: Python :: 3 :: Only
Classifier: Intended Audience :: Developers
Classifier: Operating System :: POSIX
Classifier: Operating System :: POSIX :: Linux
Classifier: Operating System :: Microsoft :: Windows
Classifier: Operating System :: Microsoft :: Windows :: Windows 7
Classifier: Topic :: Utilities
Requires-Python: >=3.4
